tests/dummy_package/__init__.py
vr_delaunay_to_voronoi/__init__.py
vr_delaunay_to_voronoi/paths.py
vr_delaunay_to_voronoi/py.typed
vr_delaunay_to_voronoi/application/__init__.py
vr_delaunay_to_voronoi/application/delaunay_simplices_and_voronoi_polygons_getting.py
vr_delaunay_to_voronoi/application/main.py
vr_delaunay_to_voronoi/application/plot_preparation.py
vr_delaunay_to_voronoi/application/plotting.py
vr_delaunay_to_voronoi/application/points_getting.py
vr_delaunay_to_voronoi/voronoi/__init__.py
vr_delaunay_to_voronoi/voronoi/cell_to_edges_for_voronoi_cell_getting.py
vr_delaunay_to_voronoi/voronoi/circumscribed_circle_for_triangle_points_getting.py
vr_delaunay_to_voronoi/voronoi/delaunay_tesselation_getting.py
vr_delaunay_to_voronoi/voronoi/long_line_endpoints_and_line_indices_getting.py
vr_delaunay_to_voronoi/voronoi/ordered_edges_by_edge_indices_getting.py
vr_delaunay_to_voronoi/voronoi/outer_cell_closing.py
vr_delaunay_to_voronoi/voronoi/polygon_index_to_polygon_for_cells_getting.py
vr_delaunay_to_voronoi/voronoi/voronoi_getting.py
vr_delaunay_to_voronoi-1.0.25.dist-info/METADATA
vr_delaunay_to_voronoi-1.0.25.dist-info/WHEEL
vr_delaunay_to_voronoi-1.0.25.dist-info/top_level.txt
vr_delaunay_to_voronoi-1.0.25.dist-info/RECORD
