Metadata-Version: 2.1
Name: vr-delaunay-to-voronoi
Version: 1.0.25
Summary: Convert from Delaunay tesselation to Voronoi triangulation.
Home-page: https://gitlab.com/dfki/ra/ni/ol/iml/vr/vr.delaunay_to_voronoi/
Author: Bengt Lüers
Author-email: bengt.lueers@gmail.com
Maintainer: Bengt Lüers
Maintainer-email: bengt.lueers@gmail.com
Classifier: Development Status :: 5 - Production/Stable
Classifier: Intended Audience :: Developers
Classifier: Intended Audience :: Science/Research
Classifier: Topic :: Software Development
Classifier: Topic :: Software Development :: Libraries
Classifier: Topic :: Software Development :: Libraries :: Python Modules
Classifier: Programming Language :: Python
Classifier: Programming Language :: Python :: 3
Classifier: Programming Language :: Python :: 3 :: Only
Classifier: Programming Language :: Python :: 3.8
Classifier: Programming Language :: Python :: 3.9
Classifier: Programming Language :: Python :: 3.10
